{
 "slug": "gimpo",
 "name": "김포시",
 "region": "경기도",
 "headline": "김포시 기억궁전",
 "intro": "내부 방은 렌더링하지 않고, 실제 3D 지도 배경 위에 명소 마커를 얹습니다.",
 "center": {
  "lat": 37.646,
  "lon": 126.63717,
  "zoom": 12
 },
 "landmarks": [
  {
   "name": "애기봉평화생태공원",
   "desc": "한강 하구 너머 북녘이 보이는 전망 공원.",
   "h": 12,
   "lon": 126.594816,
   "lat": 37.744524
  },
  {
   "name": "대명항",
   "desc": "함상공원을 낀 수도권 가까운 어항.",
   "h": 12,
   "lon": 126.541728,
   "lat": 37.639372
  },
  {
   "name": "덕포진",
   "desc": "조선 수군이 강화 해협을 지키던 포대 유적.",
   "h": 12,
   "lon": 126.535582,
   "lat": 37.651039
  },
  {
   "name": "김포함상공원",
   "desc": "퇴역 상륙함을 전시한 해양 안보 공원.",
   "h": 12,
   "lon": 126.539273,
   "lat": 37.640617
  },
  {
   "name": "문수산성",
   "desc": "강화를 마주 보는 조선 시대 산성.",
   "h": 12,
   "lon": 126.530995,
   "lat": 37.742036
  },
  {
   "name": "장릉",
   "desc": "인조의 아버지 원종이 잠든 조선 왕릉.",
   "h": 12,
   "lon": 126.711135,
   "lat": 37.61303
  },
  {
   "name": "김포아트빌리지",
   "desc": "한옥과 공방이 어우러진 문화예술 마을.",
   "h": 12,
   "lon": 126.695889,
   "lat": 37.646546
  },
  {
   "name": "라베니체",
   "desc": "수로를 낀 유럽풍 카페·먹거리 거리.",
   "h": 12,
   "lon": 126.678469,
   "lat": 37.64203
  },
  {
   "name": "우저서원",
   "desc": "조선 명장 조헌을 모신 서원.",
   "h": 12,
   "lon": 126.693926,
   "lat": 37.626713
  },
  {
   "name": "김포국제조각공원",
   "desc": "야외 조각과 평화를 주제로 한 공원.",
   "h": 12,
   "lon": 126.554024,
   "lat": 37.721069
  }
 ]
}